transformer_ranker/__init__.py
transformer_ranker/datacleaner.py
transformer_ranker/embedder.py
transformer_ranker/ranker.py
transformer_ranker/utils.py
transformer_ranker/estimators/__init__.py
transformer_ranker/estimators/base.py
transformer_ranker/estimators/hscore.py
transformer_ranker/estimators/logme.py
transformer_ranker/estimators/nearestneighbors.py
transformer_ranker-0.2.0.dist-info/licenses/LICENSE
transformer_ranker-0.2.0.dist-info/METADATA
transformer_ranker-0.2.0.dist-info/WHEEL
transformer_ranker-0.2.0.dist-info/top_level.txt
transformer_ranker-0.2.0.dist-info/RECORD
