Metadata-Version: 2.4
Name: transformer-ranker
Version: 0.2.0
Summary: Efficiently find the best-suited language model (LM) for your NLP task
Author-email: Lukas Garbas <lukas.garbaciauskas@informatik.hu-berlin.de>
License: MIT License
Project-URL: Homepage, https://github.com/flairNLP/transformer-ranker
Project-URL: Repository, https://github.com/flairNLP/transformer-ranker
Project-URL: Documentation, https://github.com/flairNLP/transformer-ranker/tree/main/examples
Keywords: transferability,language models
Classifier: Development Status :: 3 - Alpha
Classifier: Programming Language :: Python :: 3
Classifier: License :: OSI Approved :: MIT License
Classifier: Operating System :: OS Independent
Requires-Python: >=3.9
License-File: LICENSE
Requires-Dist: accelerate
Requires-Dist: datasets
Requires-Dist: sentencepiece
Requires-Dist: tokenizers
Requires-Dist: torch
Requires-Dist: torchmetrics
Requires-Dist: tqdm
Requires-Dist: transformers
Provides-Extra: testing
Requires-Dist: pytest; extra == "testing"
Provides-Extra: dev
Requires-Dist: black; extra == "dev"
Requires-Dist: isort; extra == "dev"
Requires-Dist: ruff; extra == "dev"
Dynamic: license-file
